cb_advanced_trade/__init__.py
cb_advanced_trade/authentication.py
cb_advanced_trade/constants.py
cb_advanced_trade/endpoints.py
cb_advanced_trade/sessions.py
cb_advanced_trade/utils.py
cb_advanced_trade/websockets.py
cb_advanced_trade-0.0.4.dist-info/LICENSE
cb_advanced_trade-0.0.4.dist-info/METADATA
cb_advanced_trade-0.0.4.dist-info/WHEEL
cb_advanced_trade-0.0.4.dist-info/top_level.txt
cb_advanced_trade-0.0.4.dist-info/RECORD
