Metadata-Version: 2.1
Name: cb-advanced-trade
Version: 0.0.4
Summary: Coinbase Advanced Trade API client library.
Home-page: https://github.com/ClaudiuDrug/cb-advanced-trade
Author: Claudiu DRUG
Author-email: claudiu.drug@outlook.com
License: MIT License
Project-URL: Bug Tracker, https://github.com/ClaudiuDrug/cb-advanced-trade/issues
Classifier: Programming Language :: Python :: 3.7
Classifier: Programming Language :: Python :: 3.8
Classifier: Programming Language :: Python :: 3.9
Classifier: Programming Language :: Python :: 3.10
Classifier: License :: OSI Approved :: MIT License
Classifier: Operating System :: Microsoft :: Windows :: Windows 10
Classifier: Operating System :: POSIX :: Linux
Classifier: Intended Audience :: Developers
Classifier: Natural Language :: English
Classifier: Topic :: Software Development :: Libraries :: Python Modules
Classifier: Topic :: Utilities
Requires-Python: >=3.7
License-File: LICENSE
Requires-Dist: requests (>=2.28.2)
Requires-Dist: requests-cache (>=1.0.0)
Requires-Dist: requests-toolbelt (>=0.10.1)
Requires-Dist: urllib3 (>=1.26.14)
Requires-Dist: websocket-client (>=1.5.1)
